voodoodal/__init__.py
voodoodal/pydal_db_validators.py
voodoodal/voodoodal.py
voodoodal-1.1.0.dist-info/LICENSE
voodoodal-1.1.0.dist-info/METADATA
voodoodal-1.1.0.dist-info/WHEEL
voodoodal-1.1.0.dist-info/top_level.txt
voodoodal-1.1.0.dist-info/RECORD
