Metadata-Version: 2.1
Name: voodoodal
Version: 1.1.0
Summary: voodoodal - model builder for pydal
Home-page: https://github.com/valq7711/voodoodal
Author: Valery Kucherov <valq7711@gmail.com>
Author-email: valq7711@gmail.com
Maintainer: Valery Kucherov <valq7711@gmail.com>
Maintainer-email: valq7711@gmail.com
License: MIT
Keywords: python pydal autocomplete
Platform: any
Classifier: Development Status :: 4 - Beta
Classifier: Environment :: Web Environment
Classifier: Intended Audience :: Developers
Classifier: License :: OSI Approved :: MIT License
Classifier: Operating System :: OS Independent
Classifier: Programming Language :: Python :: 3.7
Classifier: Programming Language :: Python :: 3.8
Classifier: Programming Language :: Python :: 3.9
Classifier: Topic :: Internet :: WWW/HTTP :: HTTP Servers
Classifier: Topic :: Software Development :: Libraries :: Python Modules
Requires-Python: >=3.7
License-File: LICENSE
Requires-Dist: pydal
